setup.cfg
setup.py
gdrive/__init__.py
gdrive/client.py
gdrive_client.egg-info/PKG-INFO
gdrive_client.egg-info/SOURCES.txt
gdrive_client.egg-info/dependency_links.txt
gdrive_client.egg-info/pbr.json
gdrive_client.egg-info/requires.txt
gdrive_client.egg-info/top_level.txt