Metadata-Version: 1.0
Name: gdrive-client
Version: 1.0.0
Summary: An simpler lightweight  version of calling google drive apis if you only want to list/upload files
Home-page: https://github.com/loanzen/gdrive-client
Author: Suraj Arya
Author-email: suraj@loanzen.in
License: MIT
Platform: UNKNOWN
